epi2melabs_splash/__init__.py
epi2melabs_splash/_version.py
epi2melabs_splash/labextension/build_log.json
epi2melabs_splash/labextension/package.json
epi2melabs_splash/labextension/static/lib_index_js-webpack_sharing_consume_default_lumino_coreutils-webpack_sharing_consume_default-afeeb2.a6c251be8e219207d348.js
epi2melabs_splash/labextension/static/lib_index_js-webpack_sharing_consume_default_lumino_coreutils-webpack_sharing_consume_default-afeeb2.a6c251be8e219207d348.js.map
epi2melabs_splash/labextension/static/remoteEntry.d6a5964cd0f22dd43398.js
epi2melabs_splash/labextension/static/remoteEntry.d6a5964cd0f22dd43398.js.map
epi2melabs_splash/labextension/static/style.js
epi2melabs_splash/labextension/static/style_index_js.9501dbd225583dd3b5ac.js
epi2melabs_splash/labextension/static/style_index_js.9501dbd225583dd3b5ac.js.map
epi2melabs_splash/labextension/static/vendors-node_modules_lumino_polling_dist_index_es6_js.813455ede9b22b687381.js
epi2melabs_splash/labextension/static/vendors-node_modules_lumino_polling_dist_index_es6_js.813455ede9b22b687381.js.map
epi2melabs_splash-1.0.0.data/data/share/jupyter/labextensions/@epi2melabs/epi2melabs-splash/build_log.json
epi2melabs_splash-1.0.0.data/data/share/jupyter/labextensions/@epi2melabs/epi2melabs-splash/install.json
epi2melabs_splash-1.0.0.data/data/share/jupyter/labextensions/@epi2melabs/epi2melabs-splash/package.json
epi2melabs_splash-1.0.0.data/data/share/jupyter/labextensions/@epi2melabs/epi2melabs-splash/static/lib_index_js-webpack_sharing_consume_default_lumino_coreutils-webpack_sharing_consume_default-afeeb2.a6c251be8e219207d348.js
epi2melabs_splash-1.0.0.data/data/share/jupyter/labextensions/@epi2melabs/epi2melabs-splash/static/lib_index_js-webpack_sharing_consume_default_lumino_coreutils-webpack_sharing_consume_default-afeeb2.a6c251be8e219207d348.js.map
epi2melabs_splash-1.0.0.data/data/share/jupyter/labextensions/@epi2melabs/epi2melabs-splash/static/remoteEntry.d6a5964cd0f22dd43398.js
epi2melabs_splash-1.0.0.dist-info/LICENSE
epi2melabs_splash-1.0.0.dist-info/METADATA
epi2melabs_splash-1.0.0.dist-info/WHEEL
epi2melabs_splash-1.0.0.dist-info/top_level.txt
epi2melabs_splash-1.0.0.dist-info/RECORD
